rdgai/__init__.py
rdgai/apparatus.py
rdgai/classification.py
rdgai/data/generate_yaml.py
rdgai/data/language-subtag-registry.yaml
rdgai/evaluation.py
rdgai/export.py
rdgai/languages.py
rdgai/main.py
rdgai/mapper.py
rdgai/parsers.py
rdgai/prompts.py
rdgai/tei.py
rdgai/templates/assets/css/bootstrap.rdgai.min.css
rdgai/templates/assets/css/rdgai.css
rdgai/templates/assets/css/rdgai.min.css
rdgai/templates/assets/img/favicon.svg
rdgai/templates/assets/img/feather-align-left.svg
rdgai/templates/assets/img/feather-bar-chart-2.svg
rdgai/templates/assets/img/feather-check-circle.svg
rdgai/templates/assets/img/feather-code.svg
rdgai/templates/assets/img/feather-image.svg
rdgai/templates/assets/img/feather-list.svg
rdgai/templates/assets/img/feather-x-circle.svg
rdgai/templates/assets/img/rdgai-favicon.png
rdgai/templates/assets/img/rdgai-logo-tall.svg
rdgai/templates/assets/js/bootstrap.min.js
rdgai/templates/assets/js/rdgai.js
rdgai/templates/report.html
rdgai/templates/server.html
rdgai/validation.py
rdgai-0.1.2.dist-info/LICENSE
rdgai-0.1.2.dist-info/METADATA
rdgai-0.1.2.dist-info/WHEEL
rdgai-0.1.2.dist-info/entry_points.txt
rdgai-0.1.2.dist-info/RECORD
