Metadata-Version: 2.3
Name: rdgai
Version: 0.1.2
Summary: Rdgai facilitates the use of LLMs for classifying transitions between variant readings in a Text Encoding Initiative (TEI) XML file containing a critical apparatus.
License: Apache-2.0
Keywords: command-line interface
Author: Robert Turnbull
Author-email: robert.turnbull@unimelb.edu.au
Requires-Python: >=3.10,<3.15
Classifier: Intended Audience :: Science/Research
Classifier: License :: OSI Approved :: Apache Software License
Classifier: Programming Language :: Python :: 3
Classifier: Programming Language :: Python :: 3.10
Classifier: Programming Language :: Python :: 3.11
Classifier: Programming Language :: Python :: 3.12
Classifier: Programming Language :: Python :: 3.13
Classifier: Topic :: Scientific/Engineering :: Artificial Intelligence
Classifier: Topic :: Software Development :: Libraries :: Python Modules
Requires-Dist: flask (>=3.0.3)
Requires-Dist: kmedoids (>=0.5.3.1)
Requires-Dist: langchain (>=0.2.1)
Requires-Dist: levenshtein (>=0.26.1)
Requires-Dist: llmloader (>=0.1.6)
Requires-Dist: lxml (>=5.2.2)
Requires-Dist: openpyxl (>=3.1.5)
Requires-Dist: pandas (>=2.2.3)
Requires-Dist: plotly (>=5.24.1)
Requires-Dist: rich (>=13.7.1)
Requires-Dist: scikit-learn (>=1.5.2)
Requires-Dist: transformers (>=4.46.1)
Requires-Dist: typer (>=0.12.3)
Project-URL: Documentation, https://rbturnbull.github.io/rdgai
Project-URL: Homepage, https://github.com/rbturnbull/rdgai/
Project-URL: Repository, https://github.com/rbturnbull/rdgai/
